litmus_rm/ICCF_working.py
litmus_rm/__init__.py
litmus_rm/_types.py
litmus_rm/_utils.py
litmus_rm/fitting_methods.py
litmus_rm/gp_working.py
litmus_rm/lightcurve.py
litmus_rm/lin_scatter.py
litmus_rm/litmusclass.py
litmus_rm/logging.py
litmus_rm/mocks.py
litmus_rm/models.py
litmus_rm-0.9.0.dist-info/WHEEL
litmus_rm-0.9.0.dist-info/METADATA
litmus_rm-0.9.0.dist-info/RECORD
