Metadata-Version: 2.3
Name: litmus-rm
Version: 0.9.0
Summary: JAX-based lag recovery for AGN reverberation mapping
Author: Hugh McDougall
Author-email: Hugh McDougall <hughmcdougallemail@gmail.com>
Requires-Dist: jax==0.4.31
Requires-Dist: jaxlib>=0.4.31
Requires-Dist: jaxopt>=0.8.3
Requires-Dist: numpyro>=0.15.3
Requires-Dist: tinygp>=0.3.0
Requires-Dist: matplotlib>=3.9.2
Requires-Dist: numpy>=1.26.4
Requires-Dist: scikit-learn>1.5.2
Requires-Dist: scipy>=1.14.1
Requires-Dist: chainconsumer>=1.1.2
Requires-Dist: typing>=2.50
Requires-Dist: ipython>=8.29.0
Requires-Dist: nptyping>=2.5.0
Requires-Dist: etils ; extra == 'jaxns'
Requires-Dist: tensorflow-probability ; extra == 'jaxns'
Requires-Dist: jaxns ; extra == 'jaxns'
Requires-Python: >=3.10
Project-URL: repository, https://github.com/HughMcDougall/LITMUS
Provides-Extra: jaxns
